flucleave/__init__.py
flucleave/cleavage_json_to_csv.py
flucleave/cli.py
flucleave/config.py
flucleave/model.py
flucleave/predict.py
flucleave/test_predict.py
flucleave/train.py
flucleave/utils.py
flucleave/data/test/HP.fasta
flucleave/data/test/LP.fasta
flucleave/data/train/LPAI_HA_GISAID_20240221.fasta
flucleave/data/train/cleavage_sites.json
flucleave/data/train/training_data.csv
flucleave/model/best_model.h5
flucleave/model/final_model.h5
flucleave/model/training_log.csv
flucleave-0.1.5.dist-info/LICENSE
flucleave-0.1.5.dist-info/METADATA
flucleave-0.1.5.dist-info/WHEEL
flucleave-0.1.5.dist-info/entry_points.txt
flucleave-0.1.5.dist-info/top_level.txt
flucleave-0.1.5.dist-info/RECORD
