Metadata-Version: 2.1
Name: flucleave
Version: 0.1.5
Summary: Deep learning prediction of Influenza A virus pathogenicity from H5 and H7 cleavage sites
Author-email: Cameron Norris <cameron.norris@usda.gov>
License: MIT
Classifier: Operating System :: OS Independent
Classifier: Intended Audience :: Science/Research
Classifier: License :: OSI Approved :: MIT License
Classifier: Programming Language :: Python :: 3.8
Classifier: Topic :: Scientific/Engineering :: Bio-Informatics
Requires-Python: >=3.8
License-File: LICENSE
Requires-Dist: tensorflow>=2.8.0
Requires-Dist: pandas>=1.4.0
Requires-Dist: numpy>=1.21.0
Requires-Dist: biopython>=1.79
Requires-Dist: scikit-learn>=1.0.0
Requires-Dist: click>=8.0.0
Provides-Extra: dev
Requires-Dist: pytest>=7.0.0; extra == "dev"
Requires-Dist: black>=22.0.0; extra == "dev"
Requires-Dist: ruff>=0.1.0; extra == "dev"
Requires-Dist: mypy>=1.0.0; extra == "dev"
